Workbook
Name ChartNames: OFFSET(Lists!$A$2,0,0,MAX(1,COUNTIF(Lists!$A$2:$A$101,"?*")),1)
Name CurYear: Settings!$B$6
Name CurMonthNum: IF(ISNUMBER(Settings!$B$8),Settings!$B$8,MATCH(LEFT(Settings!$B$8,3),{"Jan","Feb","Mar","Apr","May","Jun","Jul","Aug","Sep","Oct","Nov","Dec"},0))

Sheet Instructions
A1: Monthly Dashboard Inputs
A3: How to use
A4: 1. Fill in the Settings, Charts, Footnotes, Table, Commentary and Side Table tabs. Blue text on yellow = inputs.
A5: 2. Save this workbook.
A6: 3. Open the Dashboard Builder page in Edge or Chrome and drag this workbook onto it.
A7: 4. Click "Save as PDF" (or press Ctrl+P), choose "Save as PDF", and save.
A9: Tabs
A10: Settings - titles, labels, footer, and layout options. The Notes column explains each one.
A11: "Current month" drives the month and YTD columns of the table. Current-year chart values after it are not shown.
A12: Charts - one row per chart / component / year with Jan-Dec values. Leave months blank where there is no data yet.
A13: Each distinct "Chart" name becomes its own chart. Rows with a "Component" (e.g. Contracted, Merchant) are stacked.
A14: Every chart shows the Prior year and Current year from Settings side by side, month by month,
... A46: - Your data never leaves your computer: the builder page reads the file locally in the browser.

Sheet Settings
A1: Setting | B1: Value | C1: Notes
A2: Title | B2: BLUEFIELD SOLAR HOLDINGS | C2: Large text in the top banner.
A3: Subtitle | B3: August 2026 Monthly Monitoring Dashboard | C3: Smaller line under the title.
A4: Period label | B4: MONTH ENDED AUGUST 31, 2026 | C4: Shown at the top right of the banner.
A5: Header color | B5: #1F3B6E | C5: Hex color for the banner and section headers, e.g. #1F3B6E.
A6: Current year | B6: 2026 | C6: Year whose values are the solid bars.
A7: Prior year | B7: 2025 | C7: Year whose values are the lighter bars next to them.
A8: Current month | B8: Aug | C8: The month being reported. Drives Month Actual and YTD (Jan through this month) in the table.
A9: Chart section title | B9: Monthly Performance - 2026 vs. 2025 | C9: Header above the charts.
A10: Data labels | B10: Both years | C10: Which bars get value labels: Both years / This year / None.
A11: Chart columns | B11: Auto | C11: Auto = 1 column for up to 3 charts, 2 columns for more.
A12: Table title | B12: Operating and Financial Performance vs. EV Case - YTD & Monthly | C12: Header above the comparison table.
A13: Month heading | C13: Heading over the monthly columns. Leave blank to use the Current month (e.g. August).
A14: YTD heading | C14: Heading over the year-to-date columns. Leave blank for "YTD Through August".
A15: Actual label | B15: Actual | C15: Column label for actual values.
A16: Comparison label | B16: EV Case | C16: Column label for the comparison case (EV Case, Budget, Forecast...).
A17: Variance label | B17: Variance | C17: Column label for the variance.
A18: Negative numbers | B18: Parentheses | C18: Parentheses: (1.8) Minus sign: -1.8
A19: Side panel type | B19: Commentary | C19: Commentary / Table / Table + Commentary / None.
A20: Side panel title | B20: Maintenance Commentary | C20: Header of the bottom-right box.
A21: Side panel width % | B21: 30 | C21: Width of the bottom-right box as a share of the page (15-50).
A22: Footer | B22: Sources: Bluefield monthly operating reports; 2026 EV Case model. Fictional example data. | C22: Sources line at the bottom of the page.
A23: Page size | B23: Letter | C23: Letter or A4 (always landscape).
A24: Pro-rated note | C24: Optional wording for the EV Basis footnote under the table. Blank = "EV Case pro-rated from quarterly figures on a straight-line monthly basis; it does not reflect seasonality within the quarter." You can use {basis} (quarterly / semi-annual / annual), {period} (quarter / half-year / year) and {comparison} (the Comparison label).
A25: Include DSCR page | B25: Auto | C25: Auto = add page 2 (Debt Service Coverage) when the Debt Service tab has data. Yes / No to force it.
A26: DSCR page title | B26: Debt Service Coverage - LTM Basis | C26: Header above the DSCR charts on page 2.
A27: Quarters shown | B27: 8 | C27: How many of the most recent quarters page 2 shows (1-12), as far as the Debt Service tab has data. LTM DSCR needs the 3 quarters before each one.
A28: Distribution lock-up DSCR | B28: 1.2 | C28: Distribution lock-up covenant, e.g. 1.20. Drawn as a reference line. Leave blank and it does not appear anywhere.
A29: Default DSCR | B29: 1 | C29: Default covenant, e.g. 1.10. Drawn as a reference line. Leave blank and it does not appear anywhere.
A30: Reserves title | B30: DSR and O&M Reserves | C30: Header of the reserves box on page 2 (below the DSCR chart).
A31: Cash flow units | B31: $MM | C31: Units label for page 2, e.g. $MM or $000s.
A32: Cash flow decimals | B32: 1 | C32: Decimals in the page 2 cash flow table and reserves (default 1).

Sheet Charts
A1: Chart | B1: Component | C1: Year | D1: Decimals | E1: Jan | F1: Feb | G1: Mar | H1: Apr | I1: May | J1: Jun | K1: Jul | L1: Aug | M1: Sep | N1: Oct | O1: Nov | P1: Dec | Q1: YTD Method
A2: Generation (GWh) | C2: 2026 | D2: 1 | E2: 24.6 | F2: 27.3 | G2: 38.9 | H2: 44.1 | I2: 49.8 | J2: 52.4 | K2: 41.7 | L2: 47.2 | Q2: Sum
A3: Generation (GWh) | C3: 2025 | D3: 1 | E3: 22.9 | F3: 26.1 | G3: 36.4 | H3: 42.7 | I3: 47.5 | J3: 50.9 | K3: 49.6 | L3: 45.8 | M3: 39.2 | N3: 31.5 | O3: 25.4 | P3: 21.8 | Q3: Sum
A4: Revenue ($MM) | C4: 2026 | D4: 1 | E4: 1.62 | F4: 1.84 | G4: 2.57 | H4: 3.03 | I4: 3.41 | J4: 4.12 | K4: 3.46 | L4: 3.92 | Q4: Sum
A5: Revenue ($MM) | C5: 2025 | D5: 1 | E5: 1.5 | F5: 1.7 | G5: 2.4 | H5: 2.8 | I5: 3.2 | J5: 3.9 | K5: 4 | L5: 3.7 | M5: 2.9 | N5: 2.2 | O5: 1.7 | P5: 1.4 | Q5: Sum
A6: Operating income ($MM) | C6: 2026 | D6: 1 | E6: -0.41 | F6: 0.12 | G6: 0.88 | H6: 1.31 | I6: 1.69 | J6: 2.27 | K6: 1.66 | L6: 2.07 | Q6: Sum
A7: Operating income ($MM) | C7: 2025 | D7: 1 | E7: -0.6 | F7: -0.2 | G7: 0.7 | H7: 1.1 | I7: 1.5 | J7: 2 | K7: 2.2 | L7: 1.9 | M7: 1.2 | N7: 0.5 | O7: -0.1 | P7: -0.5 | Q7: Sum

Sheet Footnotes
A1: Chart | B1: Month | C1: Note
B2: Jul | C2: Plant shut down July 13-17 for a utility transformer replacement at the point of interconnection.
A3: Operating income ($MM) | B3: Jan | C3: Annual property insurance premium expensed in January.

Sheet Table
A1: Metric | B1: From Chart | C1: From Component | D1: YTD Method | E1: Prefix | F1: Suffix | G1: Decimals | H1: Better When | I1: Variance As | J1: Bold | K1: Month Actual | L1: Month EV Case | M1: YTD Actual | N1: YTD EV Case | O1: EV Basis
A2: Generation | B2: Generation (GWh) | D2: Sum | F2: GWh | G2: 1 | H2: Higher | K2: =IF($C2="",SUMIFS(INDEX(Charts!$E$2:$P$500,0,CurMonthNum),Charts!$A$2:$A$500,$B2,Charts!$C$2:$C$500,CurYear),SUMIFS(INDEX(Charts!$E$2:$P$500,0,CurMonthNum),Charts!$A$2:$A$500,$B2,Charts!$C$2:$C$500,CurYear,Charts!$B$2:$B$500,$C2)) -> 47.2 | L2: 50.6 | M2: =SUMPRODUCT((Charts!$A$2:$A$500=$B2)*(Charts!$C$2:$C$500=CurYear)*((($C2="")+(Charts!$B$2:$B$500=$C2))>0)*(COLUMN(Charts!$E$1:$P$1)-COLUMN(Charts!$E$1)<CurMonthNum),Charts!$E$2:$P$500)/IF($D2="Average",CurMonthNum,1) -> 326 | N2: 351.4 | O2: Monthly
A3: Revenue | B3: Revenue ($MM) | D3: Sum | E3: $ | F3: MM | G3: 2 | H3: Higher | K3: =IF($C3="",SUMIFS(INDEX(Charts!$E$2:$P$500,0,CurMonthNum),Charts!$A$2:$A$500,$B3,Charts!$C$2:$C$500,CurYear),SUMIFS(INDEX(Charts!$E$2:$P$500,0,CurMonthNum),Charts!$A$2:$A$500,$B3,Charts!$C$2:$C$500,CurYear,Charts!$B$2:$B$500,$C3)) -> 3.92 | L3: 3.85 | M3: =SUMPRODUCT((Charts!$A$2:$A$500=$B3)*(Charts!$C$2:$C$500=CurYear)*((($C3="")+(Charts!$B$2:$B$500=$C3))>0)*(COLUMN(Charts!$E$1:$P$1)-COLUMN(Charts!$E$1)<CurMonthNum),Charts!$E$2:$P$500)/IF($D3="Average",CurMonthNum,1) -> 23.97 | N3: 25.3 | O3: Monthly
A4: O&M expense | D4: Sum | E4: $ | F4: MM | G4: 2 | H4: Lower | I4: Abs | K4: =K3-K5 -> 1.85 | L4: 1.54 | M4: =M3-M5 -> 14.38 | N4: 13.68 | O4: Pro-rated annual
A5: Operating income | B5: Operating income ($MM) | D5: Sum | E5: $ | F5: MM | G5: 2 | H5: Higher | J5: Y | K5: =IF($C5="",SUMIFS(INDEX(Charts!$E$2:$P$500,0,CurMonthNum),Charts!$A$2:$A$500,$B5,Charts!$C$2:$C$500,CurYear),SUMIFS(INDEX(Charts!$E$2:$P$500,0,CurMonthNum),Charts!$A$2:$A$500,$B5,Charts!$C$2:$C$500,CurYear,Charts!$B$2:$B$500,$C5)) -> 2.07 | L5: 2.31 | M5: =SUMPRODUCT((Charts!$A$2:$A$500=$B5)*(Charts!$C$2:$C$500=CurYear)*((($C5="")+(Charts!$B$2:$B$500=$C5))>0)*(COLUMN(Charts!$E$1:$P$1)-COLUMN(Charts!$E$1)<CurMonthNum),Charts!$E$2:$P$500)/IF($D5="Average",CurMonthNum,1) -> 9.59 | N5: 11.62 | O5: Monthly

Sheet Commentary
A1: Heading | B1: Text
A2: Interconnection | B2: Utility replaced the POI transformer July 13-17; the plant was offline for the full outage.
A3: Tracker controls | B3: Firmware update completed across all rows; stow logic retested and passed.
A4: Portfolio | B4: Routine preventive maintenance continued; no safety or environmental events.

Sheet Side Table
A1: Item | B1: Balance | C1: MoM
A2: Unrestricted cash | B2: $1.2MM | C2: -$0.3MM
A3: O&M reserve | B3: $1.85MM | C3: +$0.05MM
A4: Debt service reserve | B4: $8.62MM | C4: Flat
A5: Term loan | B5: $96.4MM | C5: -$0.9MM
A6: Revolver | B6: $0.0MM | C6: Flat

Sheet Debt Service
A1: Line item | B1: Role | C1: Q1 2024 | D1: Q2 2024 | E1: Q3 2024 | F1: Q4 2024 | G1: Q1 2025 | H1: Q2 2025 | I1: Q3 2025 | J1: Q4 2025 | K1: Q1 2026 | L1: Q2 2026 | M1: Q3 2026 | N1: Q4 2026 | O1: Q1 2027 | P1: Q2 2027 | Q1: Q3 2027 | R1: Q4 2027
A2: Revenue | B2: Revenue | C2: 5.42 | D2: 9.78 | E2: 10.21 | F2: 5.31 | G2: 5.62 | H2: 10.04 | I2: 10.52 | J2: 5.93 | K2: 6.08 | L2: 10.61 | M2: 10.94
A4: O&M | B4: Expense | C4: 1.85 | D4: 1.95 | E4: 2.05 | F4: 1.92 | G4: 2.01 | H4: 2.08 | I4: 2.17 | J4: 2.03 | K4: 2.11 | L4: 2.19 | M4: 2.24
A5: Property and Other Expenses | B5: Expense | C5: 0.48 | D5: 0.55 | E5: 0.58 | F5: 0.51 | G5: 0.49 | H5: 0.58 | I5: 0.61 | J5: 0.52 | K5: 0.53 | L5: 0.64 | M5: 0.67
A6: Total O&M costs | B6: Calculated | C6: =IF(COUNT(C2:C3,C4:C5,C9:C12)=0,"",SUM(C4:C5)) -> 2.33 | D6: =IF(COUNT(D2:D3,D4:D5,D9:D12)=0,"",SUM(D4:D5)) -> 2.5 | E6: =IF(COUNT(E2:E3,E4:E5,E9:E12)=0,"",SUM(E4:E5)) -> 2.63 | F6: =IF(COUNT(F2:F3,F4:F5,F9:F12)=0,"",SUM(F4:F5)) -> 2.43 | G6: =IF(COUNT(G2:G3,G4:G5,G9:G12)=0,"",SUM(G4:G5)) -> 2.5 | H6: =IF(COUNT(H2:H3,H4:H5,H9:H12)=0,"",SUM(H4:H5)) -> 2.66 | I6: =IF(COUNT(I2:I3,I4:I5,I9:I12)=0,"",SUM(I4:I5)) -> 2.78 | J6: =IF(COUNT(J2:J3,J4:J5,J9:J12)=0,"",SUM(J4:J5)) -> 2.55 | ... R6: =IF(COUNT(R2:R3,R4:R5,R9:R12)=0,"",SUM(R4:R5))
A7: CFADS | B7: Calculated | C7: =IF(COUNT(C2:C3,C4:C5,C9:C12)=0,"",SUM(C2:C3)-C6) -> 3.09 | D7: =IF(COUNT(D2:D3,D4:D5,D9:D12)=0,"",SUM(D2:D3)-D6) -> 7.28 | E7: =IF(COUNT(E2:E3,E4:E5,E9:E12)=0,"",SUM(E2:E3)-E6) -> 7.58 | F7: =IF(COUNT(F2:F3,F4:F5,F9:F12)=0,"",SUM(F2:F3)-F6) -> 2.88 | G7: =IF(COUNT(G2:G3,G4:G5,G9:G12)=0,"",SUM(G2:G3)-G6) -> 3.12 | H7: =IF(COUNT(H2:H3,H4:H5,H9:H12)=0,"",SUM(H2:H3)-H6) -> 7.38 | I7: =IF(COUNT(I2:I3,I4:I5,I9:I12)=0,"",SUM(I2:I3)-I6) -> 7.74 | J7: =IF(COUNT(J2:J3,J4:J5,J9:J12)=0,"",SUM(J2:J3)-J6) -> 3.38 | ... R7: =IF(COUNT(R2:R3,R4:R5,R9:R12)=0,"",SUM(R2:R3)-R6)
A9: Principal | B9: Debt service | C9: 2.3 | D9: 2.33 | E9: 2.37 | F9: 2.4 | G9: 2.42 | H9: 2.48 | I9: 2.51 | J9: 2.57 | K9: 2.62 | L9: 2.68 | M9: 2.74
A10: Interest | B10: Debt service | C10: 2.05 | D10: 2 | E10: 1.95 | F10: 1.91 | G10: 1.86 | H10: 1.81 | I10: 1.76 | J10: 1.7 | K10: 1.65 | L10: 1.6 | M10: 1.55
A11: Interest rate swap settlements | B11: Debt service | C11: 0.06 | D11: 0.05 | E11: 0.04 | F11: 0.03 | G11: 0.02 | H11: 0.01 | I11: -0.01 | J11: -0.02 | K11: -0.03 | L11: -0.02 | M11: -0.03
A12: Agency fees | B12: Debt service | C12: 0.02 | D12: 0.02 | E12: 0.02 | F12: 0.02 | G12: 0.02 | H12: 0.02 | I12: 0.02 | J12: 0.02 | K12: 0.02 | L12: 0.02 | M12: 0.02
A13: Total debt service costs | B13: Calculated | C13: =IF(COUNT(C2:C3,C4:C5,C9:C12)=0,"",SUM(C9:C12)) -> 4.43 | D13: =IF(COUNT(D2:D3,D4:D5,D9:D12)=0,"",SUM(D9:D12)) -> 4.4 | E13: =IF(COUNT(E2:E3,E4:E5,E9:E12)=0,"",SUM(E9:E12)) -> 4.38 | F13: =IF(COUNT(F2:F3,F4:F5,F9:F12)=0,"",SUM(F9:F12)) -> 4.36 | G13: =IF(COUNT(G2:G3,G4:G5,G9:G12)=0,"",SUM(G9:G12)) -> 4.32 | H13: =IF(COUNT(H2:H3,H4:H5,H9:H12)=0,"",SUM(H9:H12)) -> 4.32 | I13: =IF(COUNT(I2:I3,I4:I5,I9:I12)=0,"",SUM(I9:I12)) -> 4.28 | J13: =IF(COUNT(J2:J3,J4:J5,J9:J12)=0,"",SUM(J9:J12)) -> 4.27 | ... R13: =IF(COUNT(R2:R3,R4:R5,R9:R12)=0,"",SUM(R9:R12))
A15: DSCR - quarter | B15: Calculated | C15: =IFERROR(C7/C13,"") -> 0.697517 | D15: =IFERROR(D7/D13,"") -> 1.654545 | E15: =IFERROR(E7/E13,"") -> 1.730594 | F15: =IFERROR(F7/F13,"") -> 0.66055 | G15: =IFERROR(G7/G13,"") -> 0.722222 | H15: =IFERROR(H7/H13,"") -> 1.708333 | I15: =IFERROR(I7/I13,"") -> 1.808411 | J15: =IFERROR(J7/J13,"") -> 0.791569 | ... R15: =IFERROR(R7/R13,"")
A16: DSCR - LTM | B16: Calculated | C16: ="" | D16: ="" | E16: ="" | F16: =IF(COUNT(C7:F7)<4,"",IFERROR(SUM(C7:F7)/SUM(C13:F13),"")) -> 1.185544 | G16: =IF(COUNT(D7:G7)<4,"",IFERROR(SUM(D7:G7)/SUM(D13:G13),"")) -> 1.194731 | H16: =IF(COUNT(E7:H7)<4,"",IFERROR(SUM(E7:H7)/SUM(E13:H13),"")) -> 1.205984 | I16: =IF(COUNT(F7:I7)<4,"",IFERROR(SUM(F7:I7)/SUM(F13:I13),"")) -> 1.222222 | J16: =IF(COUNT(G7:J7)<4,"",IFERROR(SUM(G7:J7)/SUM(G13:J13),"")) -> 1.257708 | K16: =IF(COUNT(H7:K7)<4,"",IFERROR(SUM(H7:K7)/SUM(H13:K13),"")) -> 1.280794 | L16: =IF(COUNT(I7:L7)<4,"",IFERROR(SUM(I7:L7)/SUM(I13:L13),"")) -> 1.307197 | M16: =IF(COUNT(J7:M7)<4,"",IFERROR(SUM(J7:M7)/SUM(J13:M13),"")) -> 1.324166 | ... R16: =IF(COUNT(O7:R7)<4,"",IFERROR(SUM(O7:R7)/SUM(O13:R13),""))

Sheet Reserves
A1: Reserve | B1: Required | C1: Balance available
A2: Debt service reserve | B2: 8.55 | C2: 8.62
A3: O&M reserve | B3: 2.1 | C3: 1.85

Sheet DSCR Notes
A1: Heading | B1: Text
A2: Seasonality | B2: Q1 and Q4 coverage falls below 1.0x on a stand-alone basis every year; the covenants test on an LTM basis.
A3: Next test | B3: Q3 2026 test at September 30, 2026. Distributions require 1.20x LTM.

Sheet Lists
A1: Chart names
A2: =IFERROR(INDEX(Charts!$A$2:$A$500,MATCH(0,INDEX(COUNTIF($A$1:A1,Charts!$A$2:$A$500)+(Charts!$A$2:$A$500=""),0),0)),"")
A3: =IFERROR(INDEX(Charts!$A$2:$A$500,MATCH(0,INDEX(COUNTIF($A$1:A2,Charts!$A$2:$A$500)+(Charts!$A$2:$A$500=""),0),0)),"")
A4: =IFERROR(INDEX(Charts!$A$2:$A$500,MATCH(0,INDEX(COUNTIF($A$1:A3,Charts!$A$2:$A$500)+(Charts!$A$2:$A$500=""),0),0)),"")
A5: =IFERROR(INDEX(Charts!$A$2:$A$500,MATCH(0,INDEX(COUNTIF($A$1:A4,Charts!$A$2:$A$500)+(Charts!$A$2:$A$500=""),0),0)),"")
A6: =IFERROR(INDEX(Charts!$A$2:$A$500,MATCH(0,INDEX(COUNTIF($A$1:A5,Charts!$A$2:$A$500)+(Charts!$A$2:$A$500=""),0),0)),"")
A7: =IFERROR(INDEX(Charts!$A$2:$A$500,MATCH(0,INDEX(COUNTIF($A$1:A6,Charts!$A$2:$A$500)+(Charts!$A$2:$A$500=""),0),0)),"")
A8: =IFERROR(INDEX(Charts!$A$2:$A$500,MATCH(0,INDEX(COUNTIF($A$1:A7,Charts!$A$2:$A$500)+(Charts!$A$2:$A$500=""),0),0)),"")
A9: =IFERROR(INDEX(Charts!$A$2:$A$500,MATCH(0,INDEX(COUNTIF($A$1:A8,Charts!$A$2:$A$500)+(Charts!$A$2:$A$500=""),0),0)),"")
A10: =IFERROR(INDEX(Charts!$A$2:$A$500,MATCH(0,INDEX(COUNTIF($A$1:A9,Charts!$A$2:$A$500)+(Charts!$A$2:$A$500=""),0),0)),"")
A11: =IFERROR(INDEX(Charts!$A$2:$A$500,MATCH(0,INDEX(COUNTIF($A$1:A10,Charts!$A$2:$A$500)+(Charts!$A$2:$A$500=""),0),0)),"")
A12: =IFERROR(INDEX(Charts!$A$2:$A$500,MATCH(0,INDEX(COUNTIF($A$1:A11,Charts!$A$2:$A$500)+(Charts!$A$2:$A$500=""),0),0)),"")
A13: =IFERROR(INDEX(Charts!$A$2:$A$500,MATCH(0,INDEX(COUNTIF($A$1:A12,Charts!$A$2:$A$500)+(Charts!$A$2:$A$500=""),0),0)),"")
... A101: =IFERROR(INDEX(Charts!$A$2:$A$500,MATCH(0,INDEX(COUNTIF($A$1:A100,Charts!$A$2:$A$500)+(Charts!$A$2:$A$500=""),0),0)),"")
